README.rst
setup.py
iec870ree_moxa/__init__.py
iec870ree_moxa/moxa.py
iec870ree_moxa.egg-info/PKG-INFO
iec870ree_moxa.egg-info/SOURCES.txt
iec870ree_moxa.egg-info/dependency_links.txt
iec870ree_moxa.egg-info/requires.txt
iec870ree_moxa.egg-info/top_level.txt