Metadata-Version: 1.1
Name: iec870ree-moxa
Version: 0.2.2
Summary: Physical layer for using a Moxa devices with IEC870REE library
Home-page: http://www.gisce.net
Author: GISCE-TI, S.L.
Author-email: devel@gisce.net
License: AGPL3
Keywords: REE electric meters IEC 870-5-102
Platform: UNKNOWN
Classifier: Development Status :: 1 - Planning
Classifier: Topic :: Communications :: Telephony
Classifier: License :: OSI Approved :: GNU Affero General Public License v3
